napari_ui_tracer/__init__.py
napari_ui_tracer/_widget.py
napari_ui_tracer/napari.yaml
napari_ui_tracer/_tests/__init__.py
napari_ui_tracer/_tests/test_widget.py
napari_ui_tracer-0.1.2.dist-info/LICENSE
napari_ui_tracer-0.1.2.dist-info/METADATA
napari_ui_tracer-0.1.2.dist-info/WHEEL
napari_ui_tracer-0.1.2.dist-info/entry_points.txt
napari_ui_tracer-0.1.2.dist-info/top_level.txt
napari_ui_tracer-0.1.2.dist-info/RECORD
