Metadata-Version: 2.1
Name: napari-ui-tracer
Version: 0.1.2
Summary: A plugin to help understand Napari UI components and check their source code definition
Home-page: https://github.com/dalthviz/napari-ui-tracer
Author: Daniel Althviz
Author-email: dalthviz@gmail.com
License: MIT
Project-URL: Bug Tracker, https://github.com/dalthviz/napari-ui-tracer/issues
Project-URL: Documentation, https://github.com/dalthviz/napari-ui-tracer#README.md
Project-URL: Source Code, https://github.com/dalthviz/napari-ui-tracer
Project-URL: User Support, https://github.com/dalthviz/napari-ui-tracer/issues
Classifier: Development Status :: 2 - Pre-Alpha
Classifier: Framework :: napari
Classifier: Intended Audience :: Developers
Classifier: License :: OSI Approved :: MIT License
Classifier: Operating System :: OS Independent
Classifier: Programming Language :: Python
Classifier: Programming Language :: Python :: 3
Classifier: Programming Language :: Python :: 3 :: Only
Classifier: Programming Language :: Python :: 3.8
Classifier: Programming Language :: Python :: 3.9
Classifier: Programming Language :: Python :: 3.10
Classifier: Topic :: Scientific/Engineering :: Image Processing
Requires-Python: >=3.8
License-File: LICENSE
Requires-Dist: qtpy (>=2.3.0)
Provides-Extra: pre-commit
Requires-Dist: pre-commit ; extra == 'pre-commit'
Provides-Extra: pyqt5
Requires-Dist: pyqt5 ; extra == 'pyqt5'
Provides-Extra: testing
Requires-Dist: tox ; extra == 'testing'
Requires-Dist: pytest ; extra == 'testing'
Requires-Dist: pytest-cov ; extra == 'testing'
Requires-Dist: pytest-qt ; extra == 'testing'
Requires-Dist: napari ; extra == 'testing'
